<?xml version="1.0" encoding="UTF-8"?>
<metadata xml:lang="fr"><Esri><CreaDate>20180221</CreaDate><CreaTime>09371100</CreaTime><ArcGISFormat>1.0</ArcGISFormat><SyncOnce>FALSE</SyncOnce><DataProperties><itemProps><itemLocation><linkage Sync="TRUE">file://\\ZIA\C$\Users\lefrancq\Desktop\dataset_stefie\SIG\additional_map\Parcellaire_etendueL93_2011</linkage><protocol Sync="TRUE">Local Area Network</protocol></itemLocation></itemProps><copyHistory><copy source="C:\Users\lefrancq\Documents\Alteckendorf\SIG_Alteckendorf\Donnees_test_outil\Parcellaire_etendueL93_2011" dest="\\ZIA\C$\Users\lefrancq\Desktop\dataset_stefie\SIG\additional_map\Parcellaire_etendueL93_2011" date="20121016" time="10205100"></copy></copyHistory><lineage><Process ToolSource="c:\program files (x86)\arcgis\desktop10.1\ArcToolbox\Toolboxes\Data Management Tools.tbx\CalculateField" Date="20130315" Time="095625">CalculateField soil_occupp-5buses Code2012 14 VB #</Process><Process ToolSource="c:\program files (x86)\arcgis\desktop10.1\ArcToolbox\Toolboxes\Data Management Tools.tbx\CalculateField" Date="20130315" Time="095845">CalculateField soil_occupp-5buses Code2012 3 VB #</Process><Process ToolSource="c:\program files (x86)\arcgis\desktop10.1\ArcToolbox\Toolboxes\Data Management Tools.tbx\CalculateField" Date="20130315" Time="095912">CalculateField soil_occupp-5buses Code2012 6 VB #</Process><Process ToolSource="c:\program files (x86)\arcgis\desktop10.1\ArcToolbox\Toolboxes\Data Management Tools.tbx\CalculateField" Date="20130315" Time="095927">CalculateField soil_occupp-5buses Code2012 5 VB #</Process><Process ToolSource="c:\program files (x86)\arcgis\desktop10.1\ArcToolbox\Toolboxes\Data Management Tools.tbx\CalculateField" Date="20130315" Time="095944">CalculateField soil_occupp-5buses Code2012 2 VB #</Process><Process ToolSource="c:\program files (x86)\arcgis\desktop10.1\ArcToolbox\Toolboxes\Data Management Tools.tbx\CalculateField" Date="20130315" Time="095958">CalculateField soil_occupp-5buses Code2012 7 VB #</Process><Process ToolSource="c:\program files (x86)\arcgis\desktop10.1\ArcToolbox\Toolboxes\Data Management Tools.tbx\CalculateField" Date="20130315" Time="100011">CalculateField soil_occupp-5buses Code2012 8 VB #</Process><Process ToolSource="c:\program files (x86)\arcgis\desktop10.1\ArcToolbox\Toolboxes\Data Management Tools.tbx\CalculateField" Date="20130315" Time="100025">CalculateField soil_occupp-5buses Code2012 9 VB #</Process><Process ToolSource="c:\program files (x86)\arcgis\desktop10.1\ArcToolbox\Toolboxes\Data Management Tools.tbx\CalculateField" Date="20130315" Time="100038">CalculateField soil_occupp-5buses Code2012 10 VB #</Process><Process ToolSource="c:\program files (x86)\arcgis\desktop10.1\ArcToolbox\Toolboxes\Data Management Tools.tbx\CalculateField" Date="20130315" Time="100048">CalculateField soil_occupp-5buses Code2012 11 VB #</Process><Process ToolSource="c:\program files (x86)\arcgis\desktop10.1\ArcToolbox\Toolboxes\Data Management Tools.tbx\CalculateField" Date="20130315" Time="100057">CalculateField soil_occupp-5buses Code2012 12 VB #</Process><Process ToolSource="c:\program files (x86)\arcgis\desktop10.1\ArcToolbox\Toolboxes\Data Management Tools.tbx\CalculateField" Date="20130315" Time="100109">CalculateField soil_occupp-5buses Code2012 4 VB #</Process><Process ToolSource="c:\program files (x86)\arcgis\desktop10.1\ArcToolbox\Toolboxes\Data Management Tools.tbx\CalculateField" Date="20130315" Time="100141">CalculateField soil_occupp-5buses Code2012 1 VB #</Process><Process ToolSource="c:\program files (x86)\arcgis\desktop10.1\ArcToolbox\Toolboxes\Data Management Tools.tbx\CalculateField" Date="20130315" Time="100204">CalculateField soil_occupp-5buses Code2012 13 VB #</Process><Process ToolSource="C:\Program Files (x86)\ArcGIS\Desktop10.0\ArcToolbox\Toolboxes\Data Management Tools.tbx\CalculateField" Date="20160324" Time="170409">CalculateField soil_occupp-5buses code2016 "[Exploitant] &amp; [FID]" VB #</Process><Process ToolSource="C:\Program Files (x86)\ArcGIS\Desktop10.0\ArcToolbox\Toolboxes\Data Management Tools.tbx\CalculateField" Date="20160413" Time="151714">CalculateField "Land Use Alteck 2016" ProProd "[Ocsol2016] + " " + [Exploitant]" VB #</Process><Process ToolSource="C:\Program Files (x86)\ArcGIS\Desktop10.0\ArcToolbox\Toolboxes\Data Management Tools.tbx\CalculateField" Date="20160413" Time="151741">CalculateField "Land Use Alteck 2016" ProProd "[Ocsol2016] + " " + [Exploitant]" VB #</Process><Process ToolSource="C:\Program Files (x86)\ArcGIS\Desktop10.0\ArcToolbox\Toolboxes\Data Management Tools.tbx\CalculateField" Date="20160606" Time="103514">CalculateField "Land Use Alteck 2016" MassApp "[MassApplie] * [ConcProd] * [SurfAreaHa]" VB #</Process><Process ToolSource="C:\Program Files (x86)\ArcGIS\Desktop10.0\ArcToolbox\Toolboxes\Data Management Tools.tbx\CalculateField" Date="20160606" Time="103554">CalculateField "Land Use Alteck 2016" MassApp "[MassApplie] * [ConcProd] * [SurfAreaHa]" VB #</Process><Process ToolSource="C:\Program Files (x86)\ArcGIS\Desktop10.0\ArcToolbox\Toolboxes\Data Management Tools.tbx\CalculateField" Date="20160606" Time="103930">CalculateField "Land Use Alteck 2016" MassSmeto "[MassApplie] * [ConcProd] * [SurfAreaHa]" VB #</Process><Process ToolSource="C:\Program Files (x86)\ArcGIS\Desktop10.0\ArcToolbox\Toolboxes\Data Management Tools.tbx\CalculateField" Date="20160606" Time="103947">CalculateField "Land Use Alteck 2016" MassSmeto "[MassApplie] * [ConcProd] * [SurfAreaHa]" VB #</Process><Process ToolSource="C:\Program Files (x86)\ArcGIS\Desktop10.0\ArcToolbox\Toolboxes\Data Management Tools.tbx\CalculateField" Date="20160606" Time="104519">CalculateField "Land Use Alteck 2016" MassSmeto "[MassApplie] * [ConcProd] * [SurfAreaHa]" VB #</Process><Process ToolSource="C:\Program Files (x86)\ArcGIS\Desktop10.0\ArcToolbox\Toolboxes\Data Management Tools.tbx\CalculateField" Date="20160606" Time="104656">CalculateField "Land Use Alteck 2016" ApplMass "[MassApplie] * [ConcProd] * [SurfAreaHa]" VB #</Process><Process ToolSource="C:\Program Files (x86)\ArcGIS\Desktop10.0\ArcToolbox\Toolboxes\Data Management Tools.tbx\CalculateField" Date="20160606" Time="104729">CalculateField "Land Use Alteck 2016" ApplMass [MassApplie] VB #</Process><Process ToolSource="C:\Program Files (x86)\ArcGIS\Desktop10.0\ArcToolbox\Toolboxes\Data Management Tools.tbx\CalculateField" Date="20160606" Time="104800">CalculateField "Land Use Alteck 2016" ApplMass "[MassApplie] * [ConcProd_1]" VB #</Process><Process ToolSource="C:\Program Files (x86)\ArcGIS\Desktop10.0\ArcToolbox\Toolboxes\Data Management Tools.tbx\CalculateField" Date="20160606" Time="104820">CalculateField "Land Use Alteck 2016" ApplMass "[MassApplie] * [ConcProd_1] * [SurfAreaHa]" VB #</Process><Process ToolSource="C:\Program Files (x86)\ArcGIS\Desktop10.0\ArcToolbox\Toolboxes\Data Management Tools.tbx\CalculateField" Date="20160615" Time="180642">CalculateField "Land Use Alteck 2016" ApplMass "[MassApplie] * [ConcProd_1] * [SurfAreaHa]" VB #</Process><Process ToolSource="C:\Program Files (x86)\ArcGIS\Desktop10.0\ArcToolbox\Toolboxes\Data Management Tools.tbx\CalculateField" Date="20160615" Time="180814">CalculateField "Land Use Alteck 2016" ApplMass "[MassApplie] * [ConcProd_1] * [SurfAreaM2]" VB #</Process><Process ToolSource="C:\Program Files (x86)\ArcGIS\Desktop10.0\ArcToolbox\Toolboxes\Data Management Tools.tbx\CalculateField" Date="20160615" Time="180838">CalculateField "Land Use Alteck 2016" ApplMass "[MassApplie] * [ConcProd_1] * [SurfAreaM2]" VB #</Process><Process ToolSource="C:\Program Files (x86)\ArcGIS\Desktop10.0\ArcToolbox\Toolboxes\Data Management Tools.tbx\CalculateField" Date="20160615" Time="180905">CalculateField "Land Use Alteck 2016" ApplMass "[MassApplie] * [ConcProd_1] * [SurfAreaHa]" VB #</Process><Process ToolSource="C:\Program Files (x86)\ArcGIS\Desktop10.0\ArcToolbox\Toolboxes\Data Management Tools.tbx\CalculateField" Date="20160615" Time="180934">CalculateField "Land Use Alteck 2016" ApplMass "[MassApplie] * [ConcProd_1] * [SurfAreaHa] /1000" VB #</Process><Process ToolSource="C:\Program Files (x86)\ArcGIS\Desktop10.0\ArcToolbox\Toolboxes\Data Management Tools.tbx\CalculateField" Date="20160915" Time="162911">CalculateField LandUseAlteck2016 ApplMass "[MassApplie] * [SurfAreaHa] * [ConcProd_1]" VB #</Process><Process ToolSource="C:\Program Files (x86)\ArcGIS\Desktop10.0\ArcToolbox\Toolboxes\Data Management Tools.tbx\CalculateField" Date="20160915" Time="162928">CalculateField LandUseAlteck2016 ApplMass "[MassApplie] * [SurfAreaHa] * [ConcProd_1]" VB #</Process><Process ToolSource="C:\Program Files (x86)\ArcGIS\Desktop10.0\ArcToolbox\Toolboxes\Data Management Tools.tbx\CalculateField" Date="20160915" Time="165208">CalculateField LandUseAlteck2016 ApplMass "[ConcProd_1] * [SurfAreaHa] * [MassApplie]" VB #</Process><Process ToolSource="c:\program files (x86)\arcgis\desktop10.4\ArcToolbox\Toolboxes\Data Management Tools.tbx\CalculateField" Date="20180209" Time="161830">CalculateField LandUseAlteck2016 mCode !Exploitant![0:1] PYTHON_9.3 #</Process><Process ToolSource="c:\program files (x86)\arcgis\desktop10.4\ArcToolbox\Toolboxes\Data Management Tools.tbx\CalculateField" Date="20180209" Time="161846">CalculateField LandUseAlteck2016 mCode !Exploitant![0:1] PYTHON_9.3 #</Process><Process ToolSource="c:\program files (x86)\arcgis\desktop10.4\ArcToolbox\Toolboxes\Data Management Tools.tbx\CalculateField" Date="20180209" Time="161930">CalculateField LandUseAlteck2016 mCode !Exploitant![0:2] PYTHON_9.3 #</Process><Process ToolSource="c:\program files (x86)\arcgis\desktop10.4\ArcToolbox\Toolboxes\Data Management Tools.tbx\CalculateField" Date="20180209" Time="164109">CalculateField LandUseAlteck2016 mCode "!Exploitant![0:2] + "-" + !Ocsol2016![0:2]" PYTHON_9.3 #</Process><Process ToolSource="c:\program files (x86)\arcgis\desktop10.4\ArcToolbox\Toolboxes\Data Management Tools.tbx\CalculateField" Date="20180209" Time="164126">CalculateField LandUseAlteck2016 mCode "!Exploitant![0:2] + "-" + !Ocsol2016![0:2]" PYTHON_9.3 #</Process><Process ToolSource="c:\program files (x86)\arcgis\desktop10.4\ArcToolbox\Toolboxes\Data Management Tools.tbx\CalculateField" Date="20180209" Time="164514">CalculateField LandUseAlteck2016 mCode fill_empty( !Exploitant!) PYTHON_9.3 "def fill_empty(field):\n  if field:\n    return field\n  else:\n    return "test""</Process><Process ToolSource="c:\program files (x86)\arcgis\desktop10.4\ArcToolbox\Toolboxes\Data Management Tools.tbx\CalculateField" Date="20180209" Time="164624">CalculateField LandUseAlteck2016 mCode fill_empty( !Exploitant!) PYTHON_9.3 "def fill_empty(field):\n  if field != "":\n    return field\n  else:\n    return "test""</Process><Process ToolSource="c:\program files (x86)\arcgis\desktop10.4\ArcToolbox\Toolboxes\Data Management Tools.tbx\CalculateField" Date="20180209" Time="164731">CalculateField LandUseAlteck2016 mCode fill_empty( !Exploitant!) PYTHON_9.3 "def fill_empty(field):\n  if field.decode('utf-8').isspace():\n    return "test"\n  else:\n    return field"</Process><Process ToolSource="c:\program files (x86)\arcgis\desktop10.4\ArcToolbox\Toolboxes\Data Management Tools.tbx\CalculateField" Date="20180209" Time="164921">CalculateField LandUseAlteck2016 mCode fill_empty( !Exploitant!) PYTHON_9.3 "def fill_empty(field):\n  if field.decode('utf-8').isspace():\n    return "NA"\n  else:\n    return field[0:2]"</Process><Process ToolSource="c:\program files (x86)\arcgis\desktop10.4\ArcToolbox\Toolboxes\Data Management Tools.tbx\CalculateField" Date="20180209" Time="165107">CalculateField LandUseAlteck2016 mCode fill_empty( !Exploitant!) PYTHON_9.3 "def fill_empty(field):\n  if field.decode('utf-8').isspace():\n    return "NA"\n  else:\n    return field[0:2]"</Process><Process ToolSource="c:\program files (x86)\arcgis\desktop10.4\ArcToolbox\Toolboxes\Data Management Tools.tbx\CalculateField" Date="20180209" Time="165157">CalculateField LandUseAlteck2016 mCode fill_empty( !Exploitant!) PYTHON_9.3 "def fill_empty(field):\n  if field.decode('utf-8').isspace():\n    return "NA"\n  else:\n    return field[0:2] + "-""</Process><Process ToolSource="c:\program files (x86)\arcgis\desktop10.4\ArcToolbox\Toolboxes\Data Management Tools.tbx\CalculateField" Date="20180209" Time="165900">CalculateField LandUseAlteck2016 mCode fill_empty( !Exploitant!, !Ocsol2016! ) PYTHON_9.3 "def fill_empty(farmer, sol):\n  if farmer.decode('utf-8').isspace():\n    return sol\n  else:\n    return farmer[0:2] + "-" + sol[0:2]"</Process><Process ToolSource="c:\program files (x86)\arcgis\desktop10.4\ArcToolbox\Toolboxes\Data Management Tools.tbx\CalculateField" Date="20180209" Time="170357">CalculateField LandUseAlteck2016 isCrop isCropOnly( !PlotCode! ) PYTHON_9.3 "def fill_empty(farmer, sol):\n  if farmer.decode('utf-8').isspace():\n    return sol\n  else:\n    return farmer[0:2] + "-" + sol[0:2]\n\ndef isCropOnly(transect):\n  if transect.decode('utf-8').isspace():\n    return 0\n  else:\n    return 1"</Process><Process ToolSource="c:\program files (x86)\arcgis\desktop10.4\ArcToolbox\Toolboxes\Data Management Tools.tbx\CalculateField" Date="20180209" Time="170621">CalculateField LandUseAlteck2016 isCrop isCropOnly( !PlotCode! ) PYTHON_9.3 "def isCropOnly(transect):\n  if transect.decode('utf-8').isspace():\n    return 0\n  else:\n    return 1"</Process><Process ToolSource="c:\program files (x86)\arcgis\desktop10.4\ArcToolbox\Toolboxes\Data Management Tools.tbx\CalculateField" Date="20180209" Time="170811">CalculateField LandUseAlteck2016 isCrop isCropOnly( !PlotCode! ) PYTHON_9.3 "def isCropOnly(transect):\n  if transect.decode('utf-8').isspace():\n    return 0\n  elif len(transect) &gt; 1:\n    return 1\n  else:\n    return 0"</Process><Process ToolSource="c:\program files (x86)\arcgis\desktop10.4\ArcToolbox\Toolboxes\Data Management Tools.tbx\CalculateField" Date="20180209" Time="171128">CalculateField LandUseAlteck2016 isCrop isCropOnly( !PlotCode! ) PYTHON_9.3 "def isCropOnly(transect):\n  if transect.decode('utf-8').isspace():\n    return 0\n  elif len(transect) &gt; 1:\n    return 1\n  else:\n    return 0"</Process><Process ToolSource="c:\program files (x86)\arcgis\desktop10.4\ArcToolbox\Toolboxes\Data Management Tools.tbx\CalculateField" Date="20180209" Time="171140">CalculateField LandUseAlteck2016 isCrop isCropOnly( !PlotCode! ) PYTHON_9.3 "def isCropOnly(transect):\n  if transect.decode('utf-8').isspace():\n    return 0\n  elif len(transect) &gt; 1:\n    return 1\n  else:\n    return 0"</Process><Process ToolSource="c:\program files (x86)\arcgis\desktop10.4\ArcToolbox\Toolboxes\Data Management Tools.tbx\CalculateField" Date="20180209" Time="171706">CalculateField LandUseAlteck2016 mCodeT getTransect( !isCrop!, !mCode!, !PlotCode!  ) PYTHON_9.3 "def getTransect(cropBool, myCode, plot_code):\n  if cropBool == 1:\n    return myCode + "-" + plot_code[0:2]\n  else:\n    return myCode\n    return 0"</Process><Process ToolSource="c:\program files (x86)\arcgis\desktop10.4\ArcToolbox\Toolboxes\Data Management Tools.tbx\CalculateField" Date="20180209" Time="174716">CalculateField LandUseAlteck2016 mNumCode myCode( !Exploitant! ) PYTHON_9.3 "def myCode(farmer):\n  farmers = ["Friess", "Speich"] \n  if farmer in farmers:\n    return farmers.index(farmer)\n  else:\n    return 100 \n"</Process><Process ToolSource="c:\program files (x86)\arcgis\desktop10.4\ArcToolbox\Toolboxes\Data Management Tools.tbx\CalculateField" Date="20180209" Time="175228">CalculateField LandUseAlteck2016 mNumCode myCode( !Exploitant! ) PYTHON_9.3 "def myCode(farmer):\n    farmers = ["Friess", "Speich"]\n    if farmer in farmers:\n        return(farmers.index(farmer))\n    else:\n        return 100\n"</Process><Process ToolSource="c:\program files (x86)\arcgis\desktop10.4\ArcToolbox\Toolboxes\Data Management Tools.tbx\CalculateField" Date="20180209" Time="182801">CalculateField LandUseAlteck2016 mNumCode myCode( !Exploitant!, !Ocsol2016!, !PlotCode! ) PYTHON_9.3 "def myCode(farmer, ocsol, plot_code):\n    # indexes = [11 , 12, 13, ...]\n    farmers = ["Friess", "Speich", "Mahler", "Schmitt", "Burger", "Kopp", "Matthis", "Staath", "Dutt"] # len = 9\n    plots = ["No", "Ta", "So", "Nx", "Tx", "Sx"] # len = 6\n    crops = ["Beet", "Corn", "Wheat", "Orchard", "Fallow"]\n    other_land = ["Greenery", "Grass Road", "Paved Road", "Dirt Road", "Ditch", "Dirt Road" ]# len = 7\n    if farmer in farmers:\n        final = str(farmers.index(farmer)+11)\n        # 11\n        if ocsol in crops:\n            final += str(crops.index(ocsol)+11) # 1111\n            if plot_code in plots:\n                final += str(plots.index(plot_code)+11)\n            else:\n                final += "99"\n        elif ocsol in other_land:\n            ## 99\n            final += str(other_land.index(ocsol)+21)\n            if plot_code in plots:\n                final += str(plots.index(plot_code)+11)\n            else:\n                final += "99"\n        else:\n            final += "99"\n    else:\n        final = "99" ## Means no farmer\n        if ocsol in other_land:\n            final += str(other_land.index(ocsol)+21) ## 9921\n            if plot_code in plots:\n                final += str(plots.index(plot_code)+11)\n            else:\n                final += "99"\n        elif ocsol in crops:\n            final += "909090909" # This is an error!\n        else:\n            final += "99"\n    return int(final)\n"</Process><Process ToolSource="c:\program files (x86)\arcgis\desktop10.4\ArcToolbox\Toolboxes\Data Management Tools.tbx\CalculateField" Date="20180209" Time="183705">CalculateField LandUseAlteck2016 mNumCode myCode( !Exploitant!, !Ocsol2016!, !PlotCode![0:2] ) PYTHON_9.3 "def myCode(farmer, ocsol, plot_code):\n    # indexes = [11 , 12, 13, ...]\n    farmers = ["Friess", "Speich", "Mahler", "Schmitt", "Burger", "Kopp", "Mathis", "Staath", "Dutt"] # len = 9\n    crops = ["Beet", "Corn", "Wheat", "Orchard", "Fallow"]\n    other_land = ["Greenery", "Grass Road", "Paved Road", "Dirt Road", "Ditch", "Dirt Road" ]# len = 7\n    plots = ["No", "Ta", "So", "Nx", "Tx", "Sx"] # len = 6\n\n    if farmer in farmers:\n        final = str(farmers.index(farmer)+11)\n        # 11\n        if ocsol in crops:\n            final += str(crops.index(ocsol)+11) # 1111\n            if plot_code in plots:\n                final += str(plots.index(plot_code)+11)\n            else:\n                final += "99"\n        elif ocsol in other_land:\n            ## 99\n            final += str(other_land.index(ocsol)+21)\n            if plot_code in plots:\n                final += str(plots.index(plot_code)+11)\n            else:\n                final += "99"\n        else:\n            final += "99"\n    else:\n        final = "99" ## Means no farmer\n        if ocsol in other_land:\n            final += str(other_land.index(ocsol)+21) ## 9921\n            if plot_code in plots:\n                final += str(plots.index(plot_code)+11)\n            else:\n                final += "99"\n        elif ocsol in crops:\n            final += "909090909" # This is an error!\n        else:\n            final += "99"\n    return int(final)"</Process><Process ToolSource="c:\program files (x86)\arcgis\desktop10.4\ArcToolbox\Toolboxes\Data Management Tools.tbx\CalculateField" Date="20180209" Time="184107">CalculateField LandUseAlteck2016 mNumCode myCode( !Exploitant!, !Ocsol2016!, !PlotCode![0:2] ) PYTHON_9.3 "def myCode(farmer, ocsol, plot_code):\n    # indexes = [11 , 12, 13, ...]\n    farmers = ["Friess", "Speich", "Mahler", "Schmitt", "Burger", "Kopp", "Mathis", "Staath", "Dutt"] # len = 9\n    crops = ["Beet", "Corn", "Wheat", "Orchard", "Fallow"]\n    other_land = ["Greenery", "Grass Road", "Paved Road", "Dirt Road", "Ditch", "Dirt Road" ]# len = 7\n    plots = ["No", "Ta", "So", "Nx", "Tx", "Sx"] # len = 6\n\n    if farmer in farmers:\n        final = str(farmers.index(farmer)+11)\n        # 11\n        if ocsol in crops:\n            final += str(crops.index(ocsol)+11) # 1111\n            if plot_code in plots:\n                final += str(plots.index(plot_code)+11)\n            else:\n                final += "99"\n        elif ocsol in other_land:\n            ## 99\n            final += str(other_land.index(ocsol)+21)\n            if plot_code in plots:\n                final += str(plots.index(plot_code)+11)\n            else:\n                final += "99"\n        else:\n            final += "99"\n    else:\n        final = "99" ## Means no farmer\n        if ocsol in other_land:\n            final += str(other_land.index(ocsol)+21) ## 9921\n            if plot_code in plots:\n                final += str(plots.index(plot_code)+11)\n            else:\n                final += "99"\n        elif ocsol in crops:\n            final += "88" # This is outside of the catchment.\n        else:\n            final += "99"\n    return int(final)"</Process><Process ToolSource="c:\program files (x86)\arcgis\desktop10.4\ArcToolbox\Toolboxes\Data Management Tools.tbx\CalculateField" Date="20180219" Time="142028">CalculateField LandUseAlteck2016 landCode isCropOnly( !PlotCode!) PYTHON_9.3 "def isCropOnly(plot_code):\n  if plot_code.decode('utf-8').isspace():\n    return 0\n  elif len(plot_code) &gt; 1:\n    return 1\n  else:\n    return 0"</Process><Process ToolSource="c:\program files (x86)\arcgis\desktop10.4\ArcToolbox\Toolboxes\Data Management Tools.tbx\CalculateField" Date="20180219" Time="142139">CalculateField LandUseAlteck2016 landCode landuse( !Ocsol2016! ) PYTHON_9.3 "def landuse(land):\n    landuse = {"Corn": 1, "Wheat": 2, "Oats": 3, "Alfalfa": 4, "Beet": 5,\n               "Greenery": 6, "Dirt Road": 7, "Grass Road": 8, "Paved Road": 9, "Ditch": 10,\n               "Fallow": 11, "Hedge": 12, "Orchard": 13}\n    code = landuse.get(land, 0)\n    return int(code)"</Process><Process ToolSource="c:\program files (x86)\arcgis\desktop10.4\ArcToolbox\Toolboxes\Data Management Tools.tbx\CalculateField" Date="20180219" Time="143509">CalculateField LandUseAlteck2016 PlotNum autoIncrement() PYTHON_9.3 "rec=0 \ndef autoIncrement():\n    global rec \n    pStart = 1  \n    pInterval = 1 \n    if (rec == 0):  \n        rec = pStart  \n    else:  \n        rec += pInterval  \n    return rec"</Process><Process ToolSource="c:\program files (x86)\arcgis\desktop10.4\ArcToolbox\Toolboxes\Data Management Tools.tbx\CalculateField" Date="20180219" Time="151532">CalculateField LandUseAlteck2016 PlotNum autoIncrement() PYTHON_9.3 "rec=0\ndef autoIncrement():\n    global rec\n    pStart = 1  \n    pInterval = 1\n    if (rec == 0):\n        rec = pStart\n    else:\n        rec += pInterval\n    return rec"</Process><Process ToolSource="c:\program files (x86)\arcgis\desktop10.4\ArcToolbox\Toolboxes\Data Management Tools.tbx\CalculateField" Date="20180227" Time="135433">CalculateField Landuse16_L93 mNumCode "codeFarmerCrop( !Exploitant!, !Ocsol2016! ) " PYTHON_9.3 "def codeFarmerCrop(farmer, ocsol):\n    # indexes = [11 , 12, 13, ...]\n    farmers = ["Friess", "Speich", "Mahler", "Schmitt", "Burger", "Kopp", "Mathis", "Staath", "Dutt"] # len = 9\n    crops = ["Beet", "Corn", "Wheat", "Orchard", "Fallow"]\n    # indexes = [91 , 92, 93, ...]\n    other_land = ["Greenery", "Grass Road", "Paved Road", "Dirt Road", "Ditch", "Dirt Road" ]# len = 7\n    if farmer in farmers:\n        final = str(farmers.index(farmer)+11)\n        # 11\n        if ocsol in crops:\n            final += str(crops.index(ocsol)+11) \n            # 1111 (Fries, Beet), 1112 (Friess-Corn), 1115 (Friess-Fallow), \n            # 1212 (Speich-Corn), \n            # 1312 (Mahler-Corn), \n            # 1412 (Schmitt-Corn),\n            # 1511 (Burger-Beet), 1513 (Burger-Wheat), 1515 (Burger-Fallow) \n            # 1711 (Mathis-Beet), \n            # 1612 (Kopp-Beet), \n            # 1911 (Dutt-Beet), 1912 (Dutt-Corn)\n    else:\n        final = "99" # no farmer, \n        if ocsol in other_land:\n            final += str(other_land.index(ocsol)+91) ## 9991, 9991, 9993\n        else:\n            final += "99" # No farmer, no other_land (9999, Not on catchment)\n    return int(final)"</Process></lineage></DataProperties><SyncDate>20110628</SyncDate><SyncTime>10343600</SyncTime><ModDate>20110628</ModDate><ModTime>10343600</ModTime></Esri><idinfo><native Sync="TRUE">Microsoft Windows XP Version 5.1 (Build 2600) Service Pack 3; ESRI ArcCatalog 9.2.0.1324</native><descript><langdata Sync="TRUE">fr</langdata><abstract>REQUIRED: A brief narrative summary of the data set.</abstract><purpose>REQUIRED: A summary of the intentions with which the data set was developed.</purpose></descript><citation><citeinfo><origin>REQUIRED: The name of an organization or individual that developed the data set.</origin><pubdate>REQUIRED: The date when the data set is published or otherwise made available for release.</pubdate><title Sync="TRUE">Parcellaire modifié</title><ftname Sync="TRUE">Parcellaire modifié</ftname><geoform Sync="TRUE">vector digital data</geoform><onlink Sync="TRUE">\\SPARE-PERSO-105\D\clef Marie\SIG_Alteckendorf\Parcellaire modifié.shp</onlink></citeinfo></citation><timeperd><current>REQUIRED: The basis on which the time period of content information is determined.</current><timeinfo><sngdate><caldate>REQUIRED: The year (and optionally month, or month and day) for which the data set corresponds to the ground.</caldate></sngdate></timeinfo></timeperd><status><progress>REQUIRED: The state of the data set.</progress><update>REQUIRED: The frequency with which changes and additions are made to the data set after the initial data set is completed.</update></status><spdom><bounding><westbc Sync="TRUE">7.578871</westbc><eastbc Sync="TRUE">7.591458</eastbc><northbc Sync="TRUE">48.791719</northbc><southbc Sync="TRUE">48.783611</southbc></bounding><lboundng><leftbc Sync="TRUE">985114.247760</leftbc><rightbc Sync="TRUE">985985.154151</rightbc><bottombc Sync="TRUE">2433471.414930</bottombc><topbc Sync="TRUE">2434317.335667</topbc></lboundng></spdom><keywords><theme><themekt>REQUIRED: Reference to a formally registered thesaurus or a similar authoritative source of theme keywords.</themekt><themekey>REQUIRED: Common-use word or phrase used to describe the subject of the data set.</themekey></theme></keywords><accconst>REQUIRED: Restrictions and legal prerequisites for accessing the data set.</accconst><useconst>REQUIRED: Restrictions and legal prerequisites for using the data set after access is granted.</useconst><natvform Sync="TRUE">Shapefile</natvform></idinfo><dataIdInfo><envirDesc Sync="TRUE">Microsoft Windows XP Version 5.1 (Build 2600) Service Pack 3; ESRI ArcCatalog 9.2.0.1324</envirDesc><dataLang><languageCode Sync="TRUE" value="fr"></languageCode></dataLang><idCitation><resTitle Sync="TRUE">Parcellaire modifié</resTitle><presForm><PresFormCd Sync="TRUE" value="005"></PresFormCd></presForm></idCitation><spatRpType><SpatRepTypCd Sync="TRUE" value="001"></SpatRepTypCd></spatRpType><dataExt><geoEle><GeoBndBox esriExtentType="native"><westBL Sync="TRUE">985114.24776</westBL><eastBL Sync="TRUE">985985.154151</eastBL><northBL Sync="TRUE">2434317.335667</northBL><southBL Sync="TRUE">2433471.41493</southBL><exTypeCode Sync="TRUE">1</exTypeCode></GeoBndBox></geoEle></dataExt><geoBox esriExtentType="decdegrees"><westBL Sync="TRUE">7.578871</westBL><eastBL Sync="TRUE">7.591458</eastBL><northBL Sync="TRUE">48.791719</northBL><southBL Sync="TRUE">48.783611</southBL><exTypeCode Sync="TRUE">1</exTypeCode></geoBox></dataIdInfo><metainfo><langmeta Sync="TRUE">fr</langmeta><metstdn Sync="TRUE">FGDC Content Standards for Digital Geospatial Metadata</metstdn><metstdv Sync="TRUE">FGDC-STD-001-1998</metstdv><mettc Sync="TRUE">local time</mettc><metextns><onlink Sync="TRUE">http://www.esri.com/metadata/esriprof80.html</onlink><metprof Sync="TRUE">ESRI Metadata Profile</metprof></metextns><metc><cntinfo><cntorgp><cntper>REQUIRED: The person responsible for the metadata information.</cntper><cntorg>REQUIRED: The organization responsible for the metadata information.</cntorg></cntorgp><cntaddr><addrtype>REQUIRED: The mailing and/or physical address for the organization or individual.</addrtype><city>REQUIRED: The city of the address.</city><state>REQUIRED: The state or province of the address.</state><postal>REQUIRED: The ZIP or other postal code of the address.</postal></cntaddr><cntvoice>REQUIRED: The telephone number by which individuals can speak to the organization or individual.</cntvoice></cntinfo></metc><metd Sync="TRUE">20110628</metd></metainfo><mdLang><languageCode Sync="TRUE" value="fr"></languageCode></mdLang><mdStanName Sync="TRUE">ISO 19115 Geographic Information - Metadata</mdStanName><mdStanVer Sync="TRUE">DIS_ESRI1.0</mdStanVer><mdChar><CharSetCd Sync="TRUE" value="004"></CharSetCd></mdChar><mdHrLv><ScopeCd Sync="TRUE" value="005"></ScopeCd></mdHrLv><mdHrLvName Sync="TRUE">dataset</mdHrLvName><distinfo><resdesc Sync="TRUE">Downloadable Data</resdesc><stdorder><digform><digtinfo><transize Sync="TRUE">0,018</transize><dssize Sync="TRUE">0,018</dssize></digtinfo></digform></stdorder></distinfo><distInfo><distributor><distorTran><onLineSrc><orDesc Sync="TRUE">002</orDesc><linkage Sync="TRUE">file://\\SPARE-PERSO-105\D\clef Marie\SIG_Alteckendorf\Parcellaire modifié.shp</linkage><protocol Sync="TRUE">Local Area Network</protocol></onLineSrc><transSize Sync="TRUE">0,018</transSize></distorTran><distorFormat><formatName Sync="TRUE">Shapefile</formatName></distorFormat></distributor></distInfo><spdoinfo><direct Sync="TRUE">Vector</direct><ptvctinf><esriterm Name="Parcellaire modifié"><efeatyp Sync="TRUE">Simple</efeatyp><efeageom Sync="TRUE">Polygon</efeageom><esritopo Sync="TRUE">FALSE</esritopo><efeacnt Sync="TRUE">66</efeacnt><spindex Sync="TRUE">TRUE</spindex><linrefer Sync="TRUE">FALSE</linrefer></esriterm><sdtsterm Name="Parcellaire modifié"><sdtstype Sync="TRUE">G-polygon</sdtstype><ptvctcnt Sync="TRUE">66</ptvctcnt></sdtsterm></ptvctinf></spdoinfo><spref><horizsys><cordsysn><geogcsn Sync="TRUE">GCS_NTF</geogcsn><projcsn Sync="TRUE">NTF_Lambert_II_étendu</projcsn></cordsysn><planar><mapproj><mapprojn Sync="TRUE">Lambert Conformal Conic</mapprojn><lambertc><stdparll Sync="TRUE">45.898919</stdparll><stdparll Sync="TRUE">47.696014</stdparll><longcm Sync="TRUE">2.337229</longcm><latprjo Sync="TRUE">46.800000</latprjo><feast Sync="TRUE">600000.000000</feast><fnorth Sync="TRUE">2200000.000000</fnorth></lambertc></mapproj><planci><plance Sync="TRUE">coordinate pair</plance><plandu Sync="TRUE">meters</plandu><coordrep><absres Sync="TRUE">0.000000</absres><ordres Sync="TRUE">0.000000</ordres></coordrep></planci></planar><geodetic><horizdn Sync="TRUE">D_NTF</horizdn><ellips Sync="TRUE">Clarke_1880_IGN</ellips><semiaxis Sync="TRUE">6378249.200000</semiaxis><denflat Sync="TRUE">293.466020</denflat></geodetic></horizsys></spref><refSysInfo><RefSystem><refSysID><identCode Sync="TRUE">NTF_Lambert_II_étendu</identCode></refSysID></RefSystem></refSysInfo><spatRepInfo><VectSpatRep><topLvl><TopoLevCd Sync="TRUE" value="001"></TopoLevCd></topLvl><geometObjs Name="Parcellaire modifié"><geoObjTyp><GeoObjTypCd Sync="TRUE" value="001"></GeoObjTypCd></geoObjTyp><geoObjCnt Sync="TRUE">66</geoObjCnt></geometObjs></VectSpatRep></spatRepInfo><eainfo><detailed Name="Parcellaire modifié"><enttyp><enttypl Sync="TRUE">Parcellaire modifié</enttypl><enttypt Sync="TRUE">Feature Class</enttypt><enttypc Sync="TRUE">66</enttypc></enttyp><attr><attrlabl Sync="TRUE">FID</attrlabl><attalias Sync="TRUE">FID</attalias><attrtype Sync="TRUE">OID</attrtype><attwidth Sync="TRUE">4</attwidth><atprecis Sync="TRUE">0</atprecis><attscale Sync="TRUE">0</attscale><attrdef Sync="TRUE">Internal feature number.</attrdef><attrdefs Sync="TRUE">ESRI</attrdefs><attrdomv><udom Sync="TRUE">Sequential unique whole numbers that are automatically generated.</udom></attrdomv></attr><attr><attrlabl Sync="TRUE">Shape</attrlabl><attalias Sync="TRUE">Shape</attalias><attrtype Sync="TRUE">Geometry</attrtype><attwidth Sync="TRUE">0</attwidth><atprecis Sync="TRUE">0</atprecis><attscale Sync="TRUE">0</attscale><attrdef Sync="TRUE">Feature geometry.</attrdef><attrdefs Sync="TRUE">ESRI</attrdefs><attrdomv><udom Sync="TRUE">Coordinates defining the features.</udom></attrdomv></attr><attr><attrlabl Sync="TRUE">Id</attrlabl><attalias Sync="TRUE">Id</attalias><attrtype Sync="TRUE">Number</attrtype><attwidth Sync="TRUE">6</attwidth></attr><attr><attrlabl Sync="TRUE">Item_type</attrlabl><attalias Sync="TRUE">Item_type</attalias><attrtype Sync="TRUE">Number</attrtype><attwidth Sync="TRUE">4</attwidth></attr><attr><attrlabl Sync="TRUE">Ocsol</attrlabl><attalias Sync="TRUE">Ocsol</attalias><attrtype Sync="TRUE">String</attrtype><attwidth Sync="TRUE">50</attwidth></attr></detailed></eainfo><mdDateSt Sync="TRUE">20110628</mdDateSt></metadata>
